qualif/__init__.py
qualif/qualif.py
qualif/templates/__init__.py
qualif/templates/prompt_find_website_template.txt
qualif/templates/prompt_qualification_template.txt
partenaire_qualif-0.2.4.dist-info/LICENSE
partenaire_qualif-0.2.4.dist-info/METADATA
partenaire_qualif-0.2.4.dist-info/WHEEL
partenaire_qualif-0.2.4.dist-info/top_level.txt
partenaire_qualif-0.2.4.dist-info/RECORD
