Metadata-Version: 2.1
Name: partenaire-qualif
Version: 0.2.4
Summary: A simple tool that automates the qualification of a partner(reseller/integrator/editor) by finding its website, industries, business functions and services.
Home-page: https://github.com/ymurong/partenaire_qualif.git
Author: Yanchao MURONG
Author-email: yanchao.murong@gmail.com
Classifier: Programming Language :: Python :: 3
Classifier: License :: OSI Approved :: MIT License
License-File: LICENSE
Requires-Dist: openai
Requires-Dist: pandas
Requires-Dist: httpx
Requires-Dist: validators
Requires-Dist: beautifulsoup4
Requires-Dist: importlib-resources
